{
  "version": "7",
  "dialect": "sqlite",
  "entries": [
    {
      "idx": 0,
      "version": "6",
      "when": 1779693923019,
      "tag": "0000_init",
      "breakpoints": true
    },
    {
      "idx": 1,
      "version": "6",
      "when": 1779710403380,
      "tag": "0001_add_embedding_vector",
      "breakpoints": true
    },
    {
      "idx": 2,
      "version": "6",
      "when": 1779713197867,
      "tag": "0002_message_variants",
      "breakpoints": true
    },
    {
      "idx": 3,
      "version": "6",
      "when": 1779713489730,
      "tag": "0003_chat_import_identity",
      "breakpoints": true
    },
    {
      "idx": 4,
      "version": "6",
      "when": 1779716011605,
      "tag": "0004_embeddings_unique",
      "breakpoints": true
    },
    {
      "idx": 5,
      "version": "6",
      "when": 1779728744883,
      "tag": "0005_embeddings_hub_score",
      "breakpoints": true
    },
    {
      "idx": 6,
      "version": "6",
      "when": 1779730710282,
      "tag": "0006_embeddings_source_text",
      "breakpoints": true
    },
    {
      "idx": 7,
      "version": "6",
      "when": 1779734639901,
      "tag": "0007_relational_fks",
      "breakpoints": true
    },
    {
      "idx": 8,
      "version": "6",
      "when": 1779743461349,
      "tag": "0008_turn_metadata",
      "breakpoints": true
    },
    {
      "idx": 9,
      "version": "6",
      "when": 1779755140102,
      "tag": "0009_fold_greetings",
      "breakpoints": true
    },
    {
      "idx": 10,
      "version": "6",
      "when": 1779760780368,
      "tag": "0010_chat_model",
      "breakpoints": true
    },
    {
      "idx": 11,
      "version": "6",
      "when": 1779772800000,
      "tag": "0011_provider_api_source",
      "breakpoints": true
    },
    {
      "idx": 12,
      "version": "6",
      "when": 1779820000000,
      "tag": "0012_message_gen_timing",
      "breakpoints": true
    },
    {
      "idx": 13,
      "version": "6",
      "when": 1779830000000,
      "tag": "0013_message_finish_reason",
      "breakpoints": true
    },
    {
      "idx": 14,
      "version": "6",
      "when": 1779840000000,
      "tag": "0014_chat_events",
      "breakpoints": true
    },
    {
      "idx": 15,
      "version": "6",
      "when": 1779850000000,
      "tag": "0015_chat_compact_summary",
      "breakpoints": true
    },
    {
      "idx": 16,
      "version": "6",
      "when": 1779860000000,
      "tag": "0016_assets_cas_and_image_embeddings",
      "breakpoints": true
    },
    {
      "idx": 17,
      "version": "6",
      "when": 1779828336893,
      "tag": "0017_chat_pinned_persona",
      "breakpoints": true
    },
    {
      "idx": 18,
      "version": "6",
      "when": 1779894523220,
      "tag": "0018_chat_digests",
      "breakpoints": true
    },
    {
      "idx": 19,
      "version": "6",
      "when": 1779897952277,
      "tag": "0019_chat_segments",
      "breakpoints": true
    },
    {
      "idx": 20,
      "version": "6",
      "when": 1779908511079,
      "tag": "0020_retire_embeddings_add_character_embeddings",
      "breakpoints": true
    }
  ]
}
